orbis_plugin_scoring_ner_scorer/__init__.py
orbis_plugin_scoring_ner_scorer/conditions.py
orbis_plugin_scoring_ner_scorer/main.py
orbis_plugin_scoring_ner_scorer-2.2.4.dist-info/LICENSE
orbis_plugin_scoring_ner_scorer-2.2.4.dist-info/METADATA
orbis_plugin_scoring_ner_scorer-2.2.4.dist-info/WHEEL
orbis_plugin_scoring_ner_scorer-2.2.4.dist-info/top_level.txt
orbis_plugin_scoring_ner_scorer-2.2.4.dist-info/RECORD
