Metadata-Version: 2.1
Name: orbis-plugin-scoring-ner-scorer
Version: 2.2.4
Summary: The ner_scorer scoring plugin for Orbis
Home-page: https://github.com/orbis-eval/orbis_plugin_scoring_ner_scorer
Author: fabod
License: GPL2
Platform: UNKNOWN
Requires-Python: >3.6
